cloud_client/__init__.py
cloud_client/azure.py
cloud_sustainability-0.0.2.dist-info/LICENSE
cloud_sustainability-0.0.2.dist-info/METADATA
cloud_sustainability-0.0.2.dist-info/WHEEL
cloud_sustainability-0.0.2.dist-info/top_level.txt
cloud_sustainability-0.0.2.dist-info/RECORD
